globi/__init__.py
globi/allocate.py
globi/models.py
globi/pipelines.py
globi/py.typed
globi/cli/__init__.py
globi/cli/main.py
globi/gis/__init__.py
globi/gis/epw_metadata.geojson
globi/gis/errors.py
globi/gis/geometry.py
globi/gis/utils.py
globi/gis/weather.py
globi/type_utils/__init__.py
globi/type_utils/literals.py
globi/worker/Dockerfile
globi/worker/__init__.py
globi/worker/main.py
globi/worker/initialize/Dockerfile
globi/worker/initialize/local_aws_init.py
globi-0.1.1.dist-info/METADATA
globi-0.1.1.dist-info/WHEEL
globi-0.1.1.dist-info/entry_points.txt
globi-0.1.1.dist-info/licenses/LICENSE
globi-0.1.1.dist-info/RECORD
